Topsis_Yajat_102303185/__init__.py
Topsis_Yajat_102303185/topsis.py
topsis_yajat_102303185-1.0.0.dist-info/licenses/LICENSE
topsis_yajat_102303185-1.0.0.dist-info/METADATA
topsis_yajat_102303185-1.0.0.dist-info/WHEEL
topsis_yajat_102303185-1.0.0.dist-info/entry_points.txt
topsis_yajat_102303185-1.0.0.dist-info/top_level.txt
topsis_yajat_102303185-1.0.0.dist-info/RECORD
