Metadata-Version: 2.4
Name: Topsis-Yajat-102303185
Version: 1.0.0
Summary: A Python package for TOPSIS multi-criteria decision analysis
Author: Yajat Pahuja
License: MIT
Requires-Python: >=3.6
License-File: LICENSE
Requires-Dist: pandas
Requires-Dist: numpy
Dynamic: license-file
